{
    "exercises_names" : [
        {
            "id": 0,
            "view": [
                {
                    "color": "red",
                    "symbols": "Ã"
                },
                {
                    "color": "black",
                    "symbols": "k"
                }
            ],
            "answers": [
                "Крюк с задержкой",
                "Крюк",
                "Параклит",
                "Борзый голубчик"
            ],
            "trueAnswer": "Крюк"
        },
        {
            "id": 1,
            "view": [
                {
                    "color": "red",
                    "symbols": "Ã"
                },
                {
                    "color": "black",
                    "symbols": "k"
                }
            ],
            "answers": [
                "Тихий голубчик",
                "Стопица",
                "Параклит с отсечкой",
                "Стрела простая"
            ],
            "trueAnswer": "Стопица"
        },
        {
            "id": 2,
            "view": [
                {
                    "color": "red",
                    "symbols": "Ã"
                },
                {
                    "color": "black",
                    "symbols": "k"
                }
            ],            
            "answers": [
                "Стрела громосветлая",
                "Крюк с подверткой",
                "Статья мрачная",
                "Запятая"
            ],
            "trueAnswer": "Запятая"
        }
    ]
}